pyrocketmq/__init__.py
pyrocketmq/client/__init__.py
pyrocketmq/client/client.py
pyrocketmq/client/log.py
pyrocketmq/client/producer.py
pyrocketmq/client/consumer/__init__.py
pyrocketmq/client/consumer/consumer.py
pyrocketmq/client/consumer/listener.py
pyrocketmq/client/consumer/rebalance.py
pyrocketmq/client/consumer/store.py
pyrocketmq/common/__init__.py
pyrocketmq/common/common.py
pyrocketmq/common/message.py
pyrocketmq-0.3.4.dist-info/LICENSE
pyrocketmq-0.3.4.dist-info/METADATA
pyrocketmq-0.3.4.dist-info/WHEEL
pyrocketmq-0.3.4.dist-info/top_level.txt
pyrocketmq-0.3.4.dist-info/RECORD
