Metadata-Version: 2.1
Name: pyrocketmq
Version: 0.3.4
Summary: A Python RocketMQ 4.0+ API based on JPype
Author-email: mvpboss1004 <mvpboss1004@126.com>
License: Apache License
Project-URL: Homepage, https://github.com/mvpboss1004/pyrocketmq
Project-URL: Bug Tracker, https://github.com/mvpboss1004/pyrocketmq/issues
Classifier: Operating System :: OS Independent
Classifier: Intended Audience :: Developers
Classifier: License :: OSI Approved :: Apache Software License
Classifier: Programming Language :: Python
Classifier: Programming Language :: Python :: Implementation
Classifier: Programming Language :: Python :: 3
Classifier: Programming Language :: Python :: 3.6
Classifier: Programming Language :: Python :: 3.7
Classifier: Programming Language :: Python :: 3.8
Classifier: Programming Language :: Python :: 3.9
Classifier: Programming Language :: Python :: 3.10
Classifier: Topic :: Software Development :: Libraries
Requires-Python: >=3.6
License-File: LICENSE
